schematron/__init__.py
schematron-0.0.1.dist-info/licenses/LICENSE
schematron-0.0.1.dist-info/METADATA
schematron-0.0.1.dist-info/WHEEL
schematron-0.0.1.dist-info/top_level.txt
schematron-0.0.1.dist-info/RECORD
